{"mc":{
	"skill":{
		"frameRate":24,
		"labels":[
			{"name":"normal","frame":1,"end":15}
			
			],
		"events":[
			
			],
		"frames":[
			
			{
			"res":"wjjn_01_01",
			"x":-76,
			"y":-160
			},
			{
			"res":"wjjn_01_02",
			"x":-75,
			"y":-159
			},
			{
			"res":"wjjn_01_03",
			"x":-65,
			"y":-149
			},
			{
			"res":"wjjn_01_04",
			"x":-51,
			"y":-158
			},
			{
			"res":"wjjn_01_05",
			"x":-58,
			"y":-140
			},
			{
			"res":"wjjn_01_06",
			"x":-57,
			"y":-140
			},
			{
			"res":"wjjn_01_07",
			"x":-56,
			"y":-138
			},
			{
			"res":"wjjn_01_08",
			"x":-53,
			"y":-136
			},
			{
			"res":"wjjn_02_01",
			"x":-40,
			"y":-35
			},
			{
			"res":"wjjn_02_02",
			"x":-73,
			"y":-107
			},
			{
			"res":"wjjn_02_03",
			"x":-68,
			"y":-115
			},
			{
			"res":"wjjn_02_04",
			"x":-75,
			"y":-135
			},
			{
			"res":"wjjn_02_05",
			"x":-76,
			"y":-144
			},
			{
			"res":"wjjn_02_06",
			"x":-74,
			"y":-157
			},
			{
			"res":"wjjn_02_07",
			"x":-73,
			"y":-160
			}
			]
}},
	"res":{
		"wjjn_01_02":{"x":152,"y":0,"w":149,"h":148},
		"wjjn_02_02":{"x":0,"y":293,"w":124,"h":102},
		"wjjn_01_07":{"x":240,"y":415,"w":104,"h":101},
		"wjjn_02_07":{"x":152,"y":150,"w":124,"h":153},
		"wjjn_01_05":{"x":346,"y":415,"w":103,"h":97},
		"wjjn_02_05":{"x":0,"y":152,"w":130,"h":139},
		"wjjn_01_03":{"x":278,"y":285,"w":129,"h":128},
		"wjjn_02_03":{"x":126,"y":305,"w":112,"h":110},
		"wjjn_01_06":{"x":409,"y":278,"w":101,"h":98},
		"wjjn_02_04":{"x":278,"y":153,"w":128,"h":130},
		"wjjn_02_01":{"x":431,"y":0,"w":58,"h":35},
		"wjjn_01_04":{"x":408,"y":153,"w":102,"h":123},
		"wjjn_01_08":{"x":0,"y":397,"w":109,"h":97},
		"wjjn_01_01":{"x":0,"y":0,"w":150,"h":150},
		"wjjn_02_06":{"x":303,"y":0,"w":126,"h":151}
	}}